booklet/__init__.py
booklet/main.py
booklet/serializers.py
booklet/utils.py
booklet-0.9.1.dist-info/METADATA
booklet-0.9.1.dist-info/WHEEL
booklet-0.9.1.dist-info/licenses/LICENSE
booklet-0.9.1.dist-info/RECORD
