Metadata-Version: 2.4
Name: booklet
Version: 0.9.1
Summary: A python key-value file database
Project-URL: Homepage, https://github.com/mullenkamp/booklet
Author-email: Mike Kittridge <mullenkamp1@gmail.com>
License-Expression: Apache-2.0
License-File: LICENSE
Keywords: dbm,shelve
Classifier: Development Status :: 3 - Alpha
Classifier: Intended Audience :: Developers
Classifier: License :: OSI Approved :: Apache Software License
Requires-Python: >=3.10
Requires-Dist: orjson
Requires-Dist: portalocker
Requires-Dist: uuid6>=2024.07.10
